setup.py
MusicPlayer/__init__.py
MusicPlayer/music.py
MusicPlayer/QSS/currentMusic.qss
MusicPlayer/QSS/detailSings.qss
MusicPlayer/QSS/downloadFrame.qss
MusicPlayer/QSS/header.qss
MusicPlayer/QSS/mainContent.qss
MusicPlayer/QSS/nativeMusic.qss
MusicPlayer/QSS/navigation.qss
MusicPlayer/QSS/phoneAndEMailFrame.qss
MusicPlayer/QSS/playList.qss
MusicPlayer/QSS/playWidgets.qss
MusicPlayer/QSS/recommendFrames.qss
MusicPlayer/QSS/searchArea.qss
MusicPlayer/QSS/searchLine.qss
MusicPlayer/QSS/singsFrameBase.qss
MusicPlayer/QSS/window.qss
MusicPlayer/apis/apiRequestsBase.py
MusicPlayer/apis/netEaseApi.py
MusicPlayer/apis/netEaseEncode.py
MusicPlayer/apis/qqApi.py
MusicPlayer/apis/xiamiApi.py
MusicPlayer/dbManager/dbManager.py
MusicPlayer/dbManager/userInfoManager.py
MusicPlayer/features/asyncBase.py
MusicPlayer/features/configDownloadFrameFeatures.py
MusicPlayer/features/configMainFeatures.py
MusicPlayer/features/configNativeFeatures.py
MusicPlayer/features/configNeteaseFeatures.py
MusicPlayer/features/configQQFeatures.py
MusicPlayer/features/configRecommendFrameFeatures.py
MusicPlayer/features/configXiamiFeatures.py
MusicPlayer/logger/logger.py
MusicPlayer/networks/httpBase.py
MusicPlayer/networks/network.py
MusicPlayer/resource/download_icon.png
MusicPlayer/resource/expand.png
MusicPlayer/resource/format.ico
MusicPlayer/resource/format.png
MusicPlayer/resource/login_hover.png
MusicPlayer/resource/logo.png
MusicPlayer/resource/movie.png
MusicPlayer/resource/music.png
MusicPlayer/resource/next.png
MusicPlayer/resource/next_hover.png
MusicPlayer/resource/no_music.png
MusicPlayer/resource/no_volume.png
MusicPlayer/resource/no_volume_hover.png
MusicPlayer/resource/notes.png
MusicPlayer/resource/notes2.png
MusicPlayer/resource/nouser.png
MusicPlayer/resource/pause.png
MusicPlayer/resource/pause_hover.png
MusicPlayer/resource/play.png
MusicPlayer/resource/playAll.png
MusicPlayer/resource/play_hover.png
MusicPlayer/resource/playlist.png
MusicPlayer/resource/playlist_hover.png
Music_Player.egg-info/PKG-INFO
Music_Player.egg-info/SOURCES.txt
Music_Player.egg-info/dependency_links.txt
Music_Player.egg-info/entry_points.txt
Music_Player.egg-info/requires.txt
Music_Player.egg-info/top_level.txt