Metadata-Version: 1.0
Name: Music-Player
Version: 1.0.5
Summary: A beautiful music player
Home-page: https://github.com/HuberTRoy/MusicPlayer
Author: cyrbuzz
Author-email: cyrbuzz@foxmail.com
License: MIT
Keywords: music,netease,xiami,qq,player
Platform: UNKNOWN
